{
    "team_data": [
        {
            "team_name": "Vikings",
            "FF": "15",
            "FR": "5",
            "FR TD": "2"
        },
        {
            "team_name": "Eagles",
            "FF": "13",
            "FR": "7",
            "FR TD": "0"
        },
        {
            "team_name": "Steelers",
            "FF": "13",
            "FR": "8",
            "FR TD": "1"
        },
        {
            "team_name": "Bills",
            "FF": "12",
            "FR": "8",
            "FR TD": "0"
        },
        {
            "team_name": "Broncos",
            "FF": "12",
            "FR": "9",
            "FR TD": "1"
        },
        {
            "team_name": "Texans",
            "FF": "11",
            "FR": "7",
            "FR TD": "0"
        },
        {
            "team_name": "Colts",
            "FF": "11",
            "FR": "5",
            "FR TD": "1"
        },
        {
            "team_name": "Chiefs",
            "FF": "11",
            "FR": "8",
            "FR TD": "1"
        },
        {
            "team_name": "Jets",
            "FF": "11",
            "FR": "7",
            "FR TD": "1"
        },
        {
            "team_name": "Jaguars",
            "FF": "10",
            "FR": "9",
            "FR TD": "0"
        },
        {
            "team_name": "Seahawks",
            "FF": "10",
            "FR": "7",
            "FR TD": "0"
        },
        {
            "team_name": "Cowboys",
            "FF": "9",
            "FR": "4",
            "FR TD": "1"
        },
        {
            "team_name": "Dolphins",
            "FF": "9",
            "FR": "5",
            "FR TD": "0"
        },
        {
            "team_name": "Giants",
            "FF": "9",
            "FR": "7",
            "FR TD": "0"
        },
        {
            "team_name": "Buccaneers",
            "FF": "9",
            "FR": "7",
            "FR TD": "0"
        },
        {
            "team_name": "Ravens",
            "FF": "8",
            "FR": "5",
            "FR TD": "0"
        },
        {
            "team_name": "Bears",
            "FF": "8",
            "FR": "4",
            "FR TD": "0"
        },
        {
            "team_name": "Browns",
            "FF": "8",
            "FR": "6",
            "FR TD": "1"
        },
        {
            "team_name": "Titans",
            "FF": "8",
            "FR": "4",
            "FR TD": "0"
        },
        {
            "team_name": "Chargers",
            "FF": "8",
            "FR": "9",
            "FR TD": "0"
        },
        {
            "team_name": "Commanders",
            "FF": "8",
            "FR": "7",
            "FR TD": "0"
        },
        {
            "team_name": "Falcons",
            "FF": "7",
            "FR": "5",
            "FR TD": "0"
        },
        {
            "team_name": "Bengals",
            "FF": "7",
            "FR": "6",
            "FR TD": "0"
        },
        {
            "team_name": "Lions",
            "FF": "7",
            "FR": "4",
            "FR TD": "0"
        },
        {
            "team_name": "Packers",
            "FF": "7",
            "FR": "7",
            "FR TD": "1"
        },
        {
            "team_name": "Raiders",
            "FF": "7",
            "FR": "4",
            "FR TD": "0"
        },
        {
            "team_name": "49ers",
            "FF": "7",
            "FR": "6",
            "FR TD": "0"
        },
        {
            "team_name": "Rams",
            "FF": "6",
            "FR": "4",
            "FR TD": "0"
        },
        {
            "team_name": "Patriots",
            "FF": "6",
            "FR": "4",
            "FR TD": "0"
        },
        {
            "team_name": "Cardinals",
            "FF": "6",
            "FR": "5",
            "FR TD": "1"
        },
        {
            "team_name": "Saints",
            "FF": "4",
            "FR": "6",
            "FR TD": "0"
        },
        {
            "team_name": "Panthers",
            "FF": "2",
            "FR": "2",
            "FR TD": "0"
        }
    ]
}